parse_ioc.py
parse_ioc-0.2.0.dist-info/licenses/LICENSE
parse_ioc-0.2.0.dist-info/METADATA
parse_ioc-0.2.0.dist-info/WHEEL
parse_ioc-0.2.0.dist-info/top_level.txt
parse_ioc-0.2.0.dist-info/RECORD
