Metadata-Version: 2.4
Name: parse_ioc
Version: 0.2.0
Summary: Parse a list of indicators into a dictionary or JSON structure for programmatic use.
Requires-Python: >=3.11
License-File: LICENSE
Dynamic: license-file
